odoo/addons/sale_order_warehouse_location/README.rst
odoo/addons/sale_order_warehouse_location/__init__.py
odoo/addons/sale_order_warehouse_location/__manifest__.py
odoo/addons/sale_order_warehouse_location/i18n/sale_order_warehouse_location.pot
odoo/addons/sale_order_warehouse_location/models/__init__.py
odoo/addons/sale_order_warehouse_location/models/sale_order.py
odoo/addons/sale_order_warehouse_location/models/stock_warehouse.py
odoo/addons/sale_order_warehouse_location/readme/CONFIGURE.md
odoo/addons/sale_order_warehouse_location/readme/CONTRIBUTORS.md
odoo/addons/sale_order_warehouse_location/readme/DESCRIPTION.md
odoo/addons/sale_order_warehouse_location/readme/USAGE.md
odoo/addons/sale_order_warehouse_location/static/description/icon.png
odoo/addons/sale_order_warehouse_location/static/description/index.html
odoo/addons/sale_order_warehouse_location/tests/__init__.py
odoo/addons/sale_order_warehouse_location/tests/test_sale_order_warehouse_location.py
odoo/addons/sale_order_warehouse_location/views/stock_warehouse_views.xml
odoo_addon_sale_order_warehouse_location-16.0.1.0.0.2.dist-info/METADATA
odoo_addon_sale_order_warehouse_location-16.0.1.0.0.2.dist-info/WHEEL
odoo_addon_sale_order_warehouse_location-16.0.1.0.0.2.dist-info/top_level.txt
odoo_addon_sale_order_warehouse_location-16.0.1.0.0.2.dist-info/RECORD
